pybuilder_pip_tools/__init__.py
pybuilder_pip_tools-1.1.0.dist-info/DESCRIPTION.rst
pybuilder_pip_tools-1.1.0.dist-info/METADATA
pybuilder_pip_tools-1.1.0.dist-info/RECORD
pybuilder_pip_tools-1.1.0.dist-info/WHEEL
pybuilder_pip_tools-1.1.0.dist-info/entry_points.txt
pybuilder_pip_tools-1.1.0.dist-info/metadata.json
pybuilder_pip_tools-1.1.0.dist-info/top_level.txt
pybuilder_pip_tools-1.1.0.dist-info/zip-safe
