Metadata-Version: 2.0
Name: pybuilder-pip-tools
Version: 1.1.0
Summary: PyBuilder plugin to generate and install requirements.txt files from project (build) dependencies
Home-page: https://github.com/timdiels/pybuilder-pip-tools
Author: VIB/BEG/UGent, Tim Diels
Author-email: info@psb.ugent.be, timdiels.m@gmail.com
License: LGPLv3
Platform: UNKNOWN
Classifier: Development Status :: 4 - Beta
Classifier: Environment :: Plugins
Classifier: Intended Audience :: Developers
Classifier: License :: OSI Approved :: GNU Lesser General Public License v3 (LGPLv3)
Classifier: Natural Language :: English
Classifier: Operating System :: OS Independent
Classifier: Programming Language :: Python :: 3.4
Classifier: Programming Language :: Python :: 3.5
Classifier: Topic :: Software Development :: Build Tools
